signal_cli_dbus_rest_api/__init__.py
signal_cli_dbus_rest_api/api/__init__.py
signal_cli_dbus_rest_api/api/about/__init__.py
signal_cli_dbus_rest_api/api/groups/__init__.py
signal_cli_dbus_rest_api/api/reactions/__init__.py
signal_cli_dbus_rest_api/api/register_verify/__init__.py
signal_cli_dbus_rest_api/api/search/__init__.py
signal_cli_dbus_rest_api/api/send/__init__.py
signal_cli_dbus_rest_api/dataclasses/__init__.py
signal_cli_dbus_rest_api/lib/__init__.py
signal_cli_dbus_rest_api/lib/dbus/__init__.py
signal_cli_dbus_rest_api/lib/helper/__init__.py
signal_cli_dbus_rest_api/openapi/assets/swagger/swagger-ui-bundle.min.js
signal_cli_dbus_rest_api/openapi/assets/swagger/swagger-ui-standalone-preset.min.js
signal_cli_dbus_rest_api/openapi/assets/swagger/swagger-ui.min.css
signal_cli_dbus_rest_api/openapi/assets/swagger/swagger.html
signal_cli_dbus_rest_api/version/__init__.py
signal_cli_dbus_rest_api-22.2.3.dist-info/LICENSE
signal_cli_dbus_rest_api-22.2.3.dist-info/METADATA
signal_cli_dbus_rest_api-22.2.3.dist-info/WHEEL
signal_cli_dbus_rest_api-22.2.3.dist-info/entry_points.txt
signal_cli_dbus_rest_api-22.2.3.dist-info/top_level.txt
signal_cli_dbus_rest_api-22.2.3.dist-info/RECORD
