Metadata-Version: 2.1
Name: signal-cli-dbus-rest-api
Version: 22.2.3
Summary: UNKNOWN
Author: Stefan Heitmüller
Author-email: stefan.heitmueller@gmx.com
License: MIT
Platform: UNKNOWN
Requires-Python: ~=3.8
License-File: LICENSE
Requires-Dist: sanic (==21.12.1)
Requires-Dist: sanic-ext (==22.1.2)
Requires-Dist: python-magic (==0.4.24)
Requires-Dist: pydbus (==0.6.0)
